README.md
setup.cfg
setup.py
AltAzRange/AltAzRange_v.py
AltAzRange/__init__.py
AltAzRange.egg-info/PKG-INFO
AltAzRange.egg-info/SOURCES.txt
AltAzRange.egg-info/dependency_links.txt
AltAzRange.egg-info/top_level.txt