Metadata-Version: 2.1
Name: AltAzRange
Version: 0.57
Summary: Simple tool to get altitude (elevation), azimuth and range between observer and object / pair of cordinates
Home-page: https://github.com/sq3tle/altazrange
Author: SQ3TLE
Author-email: sq3tle@gmail.com
License: MIT
Keywords: altitude,elevation,azimuth,distance,gps,satellite
Platform: UNKNOWN
Classifier: Development Status :: 4 - Beta
Classifier: Intended Audience :: Developers
Classifier: Topic :: Software Development :: Build Tools
Classifier: License :: OSI Approved :: MIT License
Classifier: Programming Language :: Python :: 3
Classifier: Programming Language :: Python :: 3.6
Classifier: Programming Language :: Python :: 3.7
Classifier: Programming Language :: Python :: 3.8
